CHANGELOG.txt
LICENSE.txt
MANIFEST.in
README.txt
setup.py
CBAT/BAT.py
CBAT/__init__.py
CBAT.egg-info/PKG-INFO
CBAT.egg-info/SOURCES.txt
CBAT.egg-info/dependency_links.txt
CBAT.egg-info/requires.txt
CBAT.egg-info/top_level.txt