Metadata-Version: 2.1
Name: CBAT
Version: 0.0.0.dev10
Summary: A Cyber-Based Assesment Tool.
Home-page: UNKNOWN
Author: Nanonite
Author-email: pug0builder@gmail.com
License: MIT
Platform: UNKNOWN
Classifier: Development Status :: 5 - Production/Stable
Classifier: Intended Audience :: Education
Classifier: Operating System :: Microsoft :: Windows :: Windows 10
Classifier: License :: OSI Approved :: MIT License
Classifier: Programming Language :: Python :: 3.10
License-File: LICENSE.txt
